tappayment
