Metadata-Version: 2.1
Name: TapPayment
Version: 0.0.2
Summary: Tap Payment Python Client
Home-page: https://github.com/Qasem-h/tappayment-python
Author: Qasem hajizadeh
License: MIT
Keywords: tappayment gateway,tap.company,tappayment gosell,gosell
Platform: UNKNOWN
Classifier: Development Status :: 4 - Beta
Classifier: Intended Audience :: Developers
Classifier: License :: OSI Approved :: MIT License
Classifier: Programming Language :: Python
Classifier: Programming Language :: Python :: 2
Classifier: Programming Language :: Python :: 2.7
Classifier: Programming Language :: Python :: 3
Classifier: Programming Language :: Python :: 3.4
Classifier: Programming Language :: Python :: 3.5
Classifier: Programming Language :: Python :: 3.6
Classifier: Topic :: Software Development :: Libraries :: Python Modules
